setup.py
source_file/__init__.py
source_file/ydt.py
ydt.egg-info/PKG-INFO
ydt.egg-info/SOURCES.txt
ydt.egg-info/dependency_links.txt
ydt.egg-info/entry_points.txt
ydt.egg-info/top_level.txt
ydt.egg-info/zip-safe